{"access_token": "APP_USR-440831634275781-012421-988e1a20347a7e3be13e2690b132de0f-1081428906", "token_type": "Bearer", "expires_in": 21600, "scope": "offline_access read urn:global:admin:info:/read-only urn:global:admin:info:/read-write urn:global:admin:oauth:/read-only urn:global:admin:oauth:/read-write urn:global:admin:users:/read-only urn:global:admin:users:/read-write urn:ml:all:comunication:/read-write urn:ml:all:publish-sync:/read-write urn:ml:mktp:ads:/read-write urn:ml:mktp:comunication:/read-write urn:ml:mktp:invoices:/read-write urn:ml:mktp:metrics:/read-only urn:ml:mktp:offers:/read-write urn:ml:mktp:orders-shipments:/read-write urn:ml:mktp:publish-sync:/read-write write", "user_id": 1081428906, "refresh_token": "TG-69756e646150ba0001d6385c-1081428906"}